digital/square_wave_generator/src/phase_accumulator.v
module phase_accumulator (
    input clk,
    input freq_tuning_word,
    output reg square_out
);

reg [31:0] phase_acc = 0; // Phase accumulator

initial begin
    phase_acc = 0; // Initialize phase accumulator to 0
    square_out = 0; // Initialize square wave output to 0
end

always @(posedge clk) begin

    phase_acc <= phase_acc + freq_tuning_word; // Increment the phase accumulator by the tuning word
    square_out <= phase_acc[31]; // Output the MSB of the phase accumulator as the square wave approximation of sine wave (1-bit resolution)
end

endmodule

digital/square_wave_generator/src/BCD_to_freq_tuning_word.v
module BCD_to_freq_tuning_word (
    input [3:0] bcd_digits [6:0], // 7 BCD digits (4 bits each)
    output reg freq_tuning_word // 32-bit frequency tuning word
);

initial begin
    freq_tuning_word = 0; // Initialize frequency tuning word to 0
end

always @(*) begin
    // Convert BCD digits to a single frequency value in Hz
    integer i;
    reg [19:0] digits_freq; // Maximum frequency is 1000000 Hz, which fits in 20 bits
    digits_freq = 0;
    for (i = 0; i < 7; i = i + 1) begin
        digits_freq = digits_freq * 10 + bcd_digits[i]; // Shift left and add the next digit
    end

    // Calculate the frequency tuning word for the 32-bit accumulator DDS generator with 100 MHz clock (100,000,000 Hz)
    // freq_tuning_word = (bcd_digits_freq * 2^32) / clk_freq
    freq_tuning_word = (digits_freq * 4294967296) / 100000000; // 2^32 = 4294967296
end

endmodule

digital/square_wave_generator/src/dds_generator.v
// Direct Digital Synthesis

module dds_generator (
    input clk,
    input [3:0] bcd_digits [6:0], // 7 BCD digits (4 bits each)
    output reg square_out
);

BCD_to_freq_tuning_word converter(
    .bcd_digits(bcd_digits),
    .freq_tuning_word(freq_tuning_word)
);

phase_accumulator phase_acc(
    .clk(clk),
    .freq_tuning_word(freq_tuning_word),
    .square_out(square_out)
);

endmodule

digital/square_wave_generator/src/btn_encoder.v
module btn_encoder (
    input clk,
    input btn_up,
    input btn_down,
    input next_digit,
    output reg [3:0] digits [6:0]
);
reg [2:0] current_digit = 0; // Current digit index (0-6)

always @(posedge clk) begin
    if (next_digit) begin
        current_digit <= (current_digit + 1) % 7; // Move to the next digit
    end else if (btn_up) begin
        digits[current_digit] <= (digits[current_digit] + 1) % 10; // Increment the current digit
    end else if (btn_down) begin
        digits[current_digit] <= (digits[current_digit] + 9) % 10; // Decrement the current digit (adding 9 is equivalent to subtracting 1 modulo 10)
    end
end
    
endmodule

digital/square_wave_generator/src/edge_detector.v
module edge_detector (
    input clk,
    input btn_in,
    output reg pulse_out
);

reg btn_prev; // Previous state of the button

initial begin
    btn_prev = 0; // Initialize previous button state to 0
    pulse_out = 0; // Initialize pulse output to 0
end

always @(posedge clk) begin
    pulse_out <= btn_in && !btn_prev; // Generate a pulse when the button goes from 0 to 1
    btn_prev <= btn_in; // Update the previous state of the button
end

endmodule

digital/square_wave_generator/src/btn_debouncer.v
module btn_debouncer (
    input clk,
    input noisy_btn_in,
    output reg debounced_btn_out
);

// przycisk musi być stabilny przez ~10 ms, przy zegarze 100 MHz, 10 ms = 1 000 000 taktów zegara
reg [19:0] counter; // 20-bit counter for debouncing for 10 ms at 100 MHz
reg btn_state; // Current state of the button

initial begin
    counter = 0; // Initialize counter to 0
    btn_state = 0; // Initialize button state to 0
    debounced_btn_out = 0; // Initialize debounced output to 0
end

always @(posedge clk) begin
    if (noisy_btn_in == btn_state) begin
        counter <= 0;
    end else begin
        // If the button state is different, start incrementing the counter
        counter <= counter + 1;
        if (counter == 100000) begin // If the button has been in the new state for 10 ms
            btn_state <= noisy_btn_in; // Update the stable button state
            debounced_btn_out <= noisy_btn_in; // Update the debounced output
            counter <= 0; // After all, reset the counter
        end
    end
end
    
endmodule

digital/square_wave_generator/src/btn_controller.v
module btn_controller (
    input clk,
    input btn_up,
    input btn_down,
    input next_digit,
    output reg [3:0] bcd_digits [6:0]
);

wire btn_up_pulse, btn_down_pulse, next_digit_pulse;
wire btn_up_edge_pulse, btn_down_edge_pulse, next_digit_edge_pulse;

// Debounce and edge detection for btn_up
btn_debouncer btn_up_deb (
    .clk(clk),
    .noisy_btn_in(btn_up),
    .debounced_btn_out(btn_up_pulse)
);

edge_detector btn_up_edge (
    .clk(clk),
    .btn_in(btn_up_pulse),
    .pulse_out(btn_up_edge_pulse)
);

// Debounce and edge detection for btn_down
btn_debouncer btn_down_deb (
    .clk(clk),
    .noisy_btn_in(btn_down),
    .debounced_btn_out(btn_down_pulse)
);

edge_detector btn_down_edge (
    .clk(clk),
    .btn_in(btn_down_pulse),
    .pulse_out(btn_down_edge_pulse)
);

// Debounce and edge detection for next_digit button
btn_debouncer next_digit_deb (
    .clk(clk),
    .noisy_btn_in(next_digit),
    .debounced_btn_out(next_digit_pulse)
);

edge_detector next_digit_edge (
    .clk(clk),
    .btn_in(next_digit_pulse),
    .pulse_out(next_digit_edge_pulse)
);

// Button encoder to update the BCD digits based on push-button inputs
btn_encoder encoder (
    .clk(clk),
    .btn_up(btn_up_edge_pulse),
    .btn_down(btn_down_edge_pulse),
    .next_digit(next_digit_edge_pulse),
    .digits(bcd_digits)
);

endmodule

digital/square_wave_generator/src/top_squaregenerator.v
module top_squaregenerator (
    input clk,
    input btn_up,
    input btn_down,
    input next_digit,
    output square_out
);

reg [3:0] digits [6:0]; // 7 BCD digits for frequency input

btn_controller button_controller(
    .clk(clk),
    .btn_up(btn_up),
    .btn_down(btn_down),
    .next_digit(next_digit),
    .bcd_digits(digits)
);

dds_generator dds_square_wave_generator(
    .clk(clk),
    .bcd_digits(digits),
    .square_out(square_out)
);

endmodule

digital/square_wave_generator/tb/tb_top.v
`timescale 100us/1us

module tb_top;

reg clk;
reg btn_up;
reg btn_down;
reg next_digit;
wire square_out;    

// Instantiate the top module
top_squaregenerator uut (
    .clk(clk),
    .btn_up(btn_up),
    .btn_down(btn_down),
    .next_digit(next_digit),
    .square_out(square_out)
);

// Clock generation
initial begin
    clk = 0;
    forever #10000000 clk = ~clk; // 100 MHz clock (10 ns period)
end

// Test sequence
initial begin
    $dumpfile("sim/top_squaregenerator.vcd"); // Create a VCD file for waveform viewing
    $dumpvars(0, tb_top); // Dump all variables in the testbench

    // Initialize inputs
    btn_up = 0;
    btn_down = 0;
    next_digit = 0;
    #100; // Wait for 100 ns
    // Simulate button presses to set frequency to 1234567 Hz
    // Set digit 0 to 7
    next_digit = 1; #20; // Move to digit 0 
    next_digit = 0; btn_up = 1; #10; btn_up = 0; #10; // Increment digit 0 to 7
    // Set digit 1 to 6
    next_digit = 1; #10; // Move to digit 1
    next_digit = 0; btn_up = 1; #10; btn_up = 0; #10; // Increment digit 1 to 6
    // Set digit 2 to 5
    next_digit = 1; #10; // Move to digit 2
    next_digit = 0; btn_up = 1; #10; btn_up = 0; #10; // Increment digit 2 to 5
    // Set digit 3 to 4
    next_digit = 1; #10; // Move to digit 3
    next_digit = 0; btn_up = 1; #10; btn_up = 0; #10; // Increment digit 3 to 4
    // Set digit 4 to 3
    next_digit = 1; #10; // Move to digit 4
    next_digit = 0; btn_up = 1; #10; btn_up = 0; #10; // Increment digit 4 to 3
    // Set digit 5 to 2
    next_digit = 1; #10; // Move to digit 5     
    next_digit = 0; btn_up = 1; #10; btn_up = 0; #10; // Increment digit 5 to 2
    // Set digit 6 to 1
    next_digit = 1; #10; // Move to digit 6
    next_digit = 0; btn_up = 1; #10; btn_up = 0; #10; // Increment digit 6 to 1
    // Wait for some time to observe the output
    #1000; // Wait for 1 us
    $finish; // End the simulation      

    $monitor("Time: %0t, square_out: %b", $time, square_out); // Monitor the output signal
end
    
endmodule

digital/square_wave_generator/sim/top_squaregenerator.vcd
$date
	Fri Mar  6 19:45:35 2026
$end
$version
	Icarus Verilog
$end
$timescale
	1us
$end
$scope module tb_top $end
$var wire 1 ! square_out $end
$var reg 1 " btn_down $end
$var reg 1 # btn_up $end
$var reg 1 $ clk $end
$var reg 1 % next_digit $end
$scope module uut $end
$var wire 1 " btn_down $end
$var wire 1 # btn_up $end
$var wire 1 $ clk $end
$var wire 1 % next_digit $end
$var wire 1 ! square_out $end
$scope module button_controller $end
$var wire 1 " btn_down $end
$var wire 1 # btn_up $end
$var wire 1 $ clk $end
$var wire 1 % next_digit $end
$var wire 1 & next_digit_pulse $end
$var wire 1 ' next_digit_edge_pulse $end
$var wire 1 ( btn_up_pulse $end
$var wire 1 ) btn_up_edge_pulse $end
$var wire 1 * btn_down_pulse $end
$var wire 1 + btn_down_edge_pulse $end
$scope module btn_down_deb $end
$var wire 1 $ clk $end
$var wire 1 " noisy_btn_in $end
$var reg 1 , btn_state $end
$var reg 20 - counter [19:0] $end
$var reg 1 * debounced_btn_out $end
$upscope $end
$scope module btn_down_edge $end
$var wire 1 * btn_in $end
$var wire 1 $ clk $end
$var reg 1 . btn_prev $end
$var reg 1 + pulse_out $end
$upscope $end
$scope module btn_up_deb $end
$var wire 1 $ clk $end
$var wire 1 # noisy_btn_in $end
$var reg 1 / btn_state $end
$var reg 20 0 counter [19:0] $end
$var reg 1 ( debounced_btn_out $end
$upscope $end
$scope module btn_up_edge $end
$var wire 1 ( btn_in $end
$var wire 1 $ clk $end
$var reg 1 1 btn_prev $end
$var reg 1 ) pulse_out $end
$upscope $end
$scope module encoder $end
$var wire 1 + btn_down $end
$var wire 1 ) btn_up $end
$var wire 1 $ clk $end
$var wire 1 ' next_digit $end
$var reg 3 2 current_digit [2:0] $end
$upscope $end
$scope module next_digit_deb $end
$var wire 1 $ clk $end
$var wire 1 % noisy_btn_in $end
$var reg 1 3 btn_state $end
$var reg 20 4 counter [19:0] $end
$var reg 1 & debounced_btn_out $end
$upscope $end
$scope module next_digit_edge $end
$var wire 1 & btn_in $end
$var wire 1 $ clk $end
$var reg 1 5 btn_prev $end
$var reg 1 ' pulse_out $end
$upscope $end
$upscope $end
$scope module dds_square_wave_generator $end
$var wire 1 $ clk $end
$var wire 1 ! square_out $end
$var wire 1 6 freq_tuning_word $end
$scope module converter $end
$var reg 1 6 freq_tuning_word $end
$scope begin $unm_blk_2 $end
$var reg 20 7 digits_freq [19:0] $end
$var integer 32 8 i [31:0] $end
$upscope $end
$upscope $end
$scope module phase_acc $end
$var wire 1 $ clk $end
$var wire 1 6 freq_tuning_word $end
$var reg 32 9 phase_acc [31:0] $end
$var reg 1 ! square_out $end
$upscope $end
$upscope $end
$upscope $end
$upscope $end
$enddefinitions $end
$comment Show the parameter values. $end
$dumpall
$end
#0
$dumpvars
b0 9
bx 8
bx 7
06
05
b0 4
03
b0 2
01
b0 0
0/
0.
b0 -
0,
0+
0*
0)
0(
0'
0&
0%
0$
0#
0"
0!
$end
#10000
1%
#12000
1#
0%
#13000
0#
#14000
1%
#15000
1#
0%
#16000
0#
#17000
1%
#18000
1#
0%
#19000
0#
#20000
1%
#21000
1#
0%
#22000
0#
#23000
1%
#24000
1#
0%
#25000
0#
#26000
1%
#27000
1#
0%
#28000
0#
#29000
1%
#30000
1#
0%
#31000
0#
